{
    "token": "ODc3NTXXXXXXXXXXXXXXXXXXXXXXXXXXXXXXXXXXXXXXXXXXXXXXXkyk",
    "clientID": "877556281727123486",
    "Prefix": "!",
    "Guild": "578558255392096256",
    "ServerBanRole":"899049721971220511",
    "ChannelsID": {
        "VC": "899049887788834917",
        "MEMBER": "899049887788834917",
        "DATE": "899049889072304129",
        "ErrLog": "899049902909325373",
        "VerifyID": "957637681066700861",
        "BugChannel": "901665718481850448",
        "Channels": {
            "music": "899049967858122772",
            "bot": "899049992252166144",
            "meme": "899049970341130280",
            "challenge": "899049973411381268",
            "lovely": "899049978641666098",
            "grate_post": "899049980336148510",
            "food": "901665741596659773",
            "speak_your_heart": "899049987198046259",
            "ig": "899049984635310080",
            "soti": "901665740204171284"
        }
    },
    "Emotes": {
        "Error": "❌",
        "Tick": "✔️"
    },
    "OWNER": [
        "490519932292038659"
    ]
}